grabngro/__init__.py
grabngro/client.py
grabngro-0.0.16.dist-info/METADATA
grabngro-0.0.16.dist-info/WHEEL
grabngro-0.0.16.dist-info/licenses/LICENSE
grabngro-0.0.16.dist-info/RECORD
