Metadata-Version: 2.1
Name: grabngro
Version: 0.0.16
Summary: Python client library grabngro
Project-URL: Repository, https://github.com/gro-intelligence/gro-internal/tree/main/experimental/grabngro_package
Author-email: Andrew Yatzkan <andrew.yatzkan@gro-intelligence.com>
License-File: LICENSE
Classifier: License :: OSI Approved :: MIT License
Classifier: Operating System :: OS Independent
Classifier: Programming Language :: Python :: 3
Requires-Python: >=3.7
